json_lines/__init__.py
json_lines/_gzip.py
json_lines/_lib.py
json_lines/utils.py
json_lines-0.5.0.dist-info/DESCRIPTION.rst
json_lines-0.5.0.dist-info/METADATA
json_lines-0.5.0.dist-info/RECORD
json_lines-0.5.0.dist-info/WHEEL
json_lines-0.5.0.dist-info/metadata.json
json_lines-0.5.0.dist-info/top_level.txt
